DESCRIPTION.rst
LICENSE
MANIFEST.in
README.md
setup.py
sandstone_spawner/__init__.py
sandstone_spawner/spawner.py
sandstone_spawner.egg-info/PKG-INFO
sandstone_spawner.egg-info/SOURCES.txt
sandstone_spawner.egg-info/dependency_links.txt
sandstone_spawner.egg-info/not-zip-safe
sandstone_spawner.egg-info/requires.txt
sandstone_spawner.egg-info/top_level.txt