Metadata-Version: 1.1
Name: sandstone-spawner
Version: 0.1.1
Summary: Sandstone JupyterHub Spawner
